certgenerator/__init__.py
certgenerator/__version__.py
certgenerator/callbacks.py
certgenerator/cert_exceptions.py
certgenerator/certificate.py
certgenerator/cli.py
certgenerator/decorators.py
certgenerator/tools.py
certgenerator/config/__init__.py
certgenerator/config/config.ini
certgenerator/config/csr.yaml
certgenerator/config/serial.csv
certgenerator/test/__init__.py
CertGenerator-2.2.1.dist-info/LICENSE.txt
CertGenerator-2.2.1.dist-info/METADATA
CertGenerator-2.2.1.dist-info/WHEEL
CertGenerator-2.2.1.dist-info/entry_points.txt
CertGenerator-2.2.1.dist-info/top_level.txt
CertGenerator-2.2.1.dist-info/RECORD
