Metadata-Version: 2.1
Name: CertGenerator
Version: 2.2.1
Summary: A simple command line tools to create and read CSR and P12
Home-page: https://github.com/johndoe-dev/CertGenerator.git
Author: Jonathan ULLINDAH
Author-email: jonathan.ullindah@gmail.com
License: UNKNOWN
Platform: UNKNOWN
Classifier: Development Status :: 5 - Production/Stable
Classifier: Intended Audience :: Developers
Classifier: Intended Audience :: System Administrators
Classifier: Topic :: Security
Classifier: Topic :: Utilities
Classifier: License :: OSI Approved :: MIT License
Classifier: Environment :: MacOS X
Classifier: Environment :: Console
Classifier: Programming Language :: Python :: 2.7
Classifier: Natural Language :: English
Classifier: Operating System :: MacOS :: MacOS X
Requires-Dist: click
Requires-Dist: PyYAML
Requires-Dist: pyOpenSSL
Requires-Dist: ruamel.yaml
